pillow_jpls/__init__.py
pillow_jpls/_pycharls.cp311-win_amd64.pyd
pillow_jpls/jpls_image_decoder.py
pillow_jpls/jpls_image_encoder.py
pillow_jpls/jpls_image_file.py
pillow_jpls-1.3.2.dist-info/METADATA
pillow_jpls-1.3.2.dist-info/WHEEL
pillow_jpls-1.3.2.dist-info/entry_points.txt
pillow_jpls-1.3.2.dist-info/licenses/LICENSE.md
pillow_jpls-1.3.2.dist-info/RECORD
