Metadata-Version: 2.1
Name: pillow-jpls
Version: 1.3.2
Summary: A JPEG-LS plugin for the Pillow imaging library
Author-Email: Andrew Marshall <andrew@algodynamic.com>
License: BSD-3-Clause
Project-URL: Github, https://github.com/planetmarshall/pillow-jpls
Requires-Python: >=3.7
Requires-Dist: Pillow
